idptools_parrot-1.7.5.data/scripts/parrot-cvsplit
idptools_parrot-1.7.5.data/scripts/parrot-optimize
idptools_parrot-1.7.5.data/scripts/parrot-predict
idptools_parrot-1.7.5.data/scripts/parrot-preprocess
idptools_parrot-1.7.5.data/scripts/parrot-train
parrot/__init__.py
parrot/_version.py
parrot/bayesian_optimization.py
parrot/brnn_architecture.py
parrot/brnn_plot.py
parrot/encode_sequence.py
parrot/parrot_exceptions.py
parrot/process_input_data.py
parrot/py_predictor.py
parrot/train_network.py
parrot/data/README.md
parrot/data/encoding.txt
parrot/data/res_class_dataset.tsv
parrot/data/res_regress_dataset.tsv
parrot/data/seq_class_dataset.tsv
parrot/data/seq_regress_dataset.tsv
parrot/data/seqfile.txt
parrot/data/seqfile_noIDs.txt
parrot/data/splitfile.txt
parrot/tests/__init__.py
parrot/tests/test_parrot.py
parrot/tools/__init__.py
parrot/tools/class_balancing.py
parrot/tools/cli.py
parrot/tools/dataset_warnings.py
parrot/tools/preproc.py
parrot/tools/validate_args.py
tests/__init__.py
tests/test_file_io.py
tests/test_parrot.py
idptools_parrot-1.7.5.dist-info/LICENSE
idptools_parrot-1.7.5.dist-info/METADATA
idptools_parrot-1.7.5.dist-info/WHEEL
idptools_parrot-1.7.5.dist-info/top_level.txt
idptools_parrot-1.7.5.dist-info/RECORD
