Metadata-Version: 2.1
Name: idptools-parrot
Version: 1.7.5
Author: Holehouse Lab
Author-email: degriffith@wustl.edu
License: MIT
Requires-Python: >=3.7,<3.12.0
License-File: LICENSE
Requires-Dist: cython
Requires-Dist: torch (>=1.8.0)
Requires-Dist: numpy
Requires-Dist: argparse
Requires-Dist: more-itertools
Requires-Dist: scipy
Requires-Dist: scikit-learn
Requires-Dist: matplotlib
Requires-Dist: seaborn
Requires-Dist: pandas
Provides-Extra: optimize
Requires-Dist: GPy ; extra == 'optimize'
Requires-Dist: GPyOpt ; extra == 'optimize'
